Workbook

Sheet Istruzioni
A1: Progetto GEM — Registro dei movimenti economici
A2: Aggiornamento manuale. Nessuna automazione: le righe si inseriscono a mano, i totali si ricalcolano da soli.
A4: I fogli del file
A5: Parametri | B5: Numeri di base del progetto (ospiti, prezzo, percentuali) e stime dei costi. È l'unico posto dove modificare queste cifre.
A6: Movimenti | B6: IL FOGLIO DA COMPILARE. Una riga per ogni movimento realmente avvenuto, in ordine di data.
A7: Riepilogo | B7: Si calcola da solo. Confronta l'atteso con l'effettivo e calcola margine e ripartizione 50/50. Non scriverci dentro.
A9: Codice colore
A10: Testo BLU | B10: Valore inserito a mano. Si può modificare.
A11: Sfondo GIALLO | B11: Da compilare: il valore manca ancora.
A12: Testo NERO | B12: Formula. NON sovrascrivere: si perde il calcolo.
A13: Testo VERDE | B13: Riferimento a un altro foglio di questo file.
A15: Come si registra un movimento
A16: 1. | B16: Apri il foglio 'Movimenti' e vai alla prima riga vuota.
A17: 2. | B17: Compila SOLO le colonne da A a F. La colonna G (Saldo progressivo) si calcola da sola.
A18: 3. | B18: Inserisci l'importo in colonna F sempre come numero POSITIVO, anche per i costi: è la colonna 'Tipo movimento' a stabilire il segno.
A19: 4. | B19: Scegli 'Tipo movimento' e 'Categoria' dai menu a tendina: il foglio 'Riepilogo' somma in base a quei valori esatti. Un testo scritto a mano non viene conteggiato.
A20: 5. | B20: Registra il movimento quando il denaro si muove davvero (incasso o pagamento), non quando viene emessa la fattura.
A22: Le tre voci di 'Tipo movimento'
A23: Incasso | B23: Denaro che entra. Aumenta il saldo.
A24: Costo | B24: Denaro che esce verso fornitori. Riduce il saldo ed erode il margine.
A25: Distribuzione | B25: Denaro prelevato dai soci. Riduce il saldo di cassa ma NON è un costo: non riduce il margine.
A27: Esempio di compilazione
A28: Data | B28: Tipo movimento | C28: Categoria | D28: Descrizione | E28: Ospite / Tranche | F28: Importo (€) | G28: Saldo progressivo (€)
A29: 15/10/2026 | B29: Incasso | C29: Tranche 80% | D29: Fattura n. 001 — anticipo 80% all'arrivo | E29: Tranche 80% — 36 ospiti | F29: 57.600,00 € | G29: 57.600,00 €
A30: 18/10/2026 | B30: Costo | C30: Alloggio | D30: Struttura X — acconto 36 camere singole | E30: 36 ospiti | F30: 20.000,00 € | G30: 37.600,00 €
A31: 18/10/2026 | B31: Costo | C31: Transfert | D31: Bus aeroporto — arrivo gruppo | E31: 36 ospiti | F31: 1.200,00 € | G31: 36.400,00 €
A33: Valori mostrati come testo, solo per illustrare il formato atteso. In 'Movimenti' vanno inseriti come data e come numero.

Sheet Parametri
A1: Parametri di progetto
A2: Le celle in blu sono modificabili a mano. Quelle in giallo mancano ancora.
A4: Base dell'accordo
A5: Numero ospiti | B5: 36 | C5: Dato corrente. Ogni variazione cambia il corrispettivo.
A6: Corrispettivo netto per ospite | B6: 2000 | C6: 2.000 € netti / 90 giorni. Concordato a voce, non per iscritto.
A7: Giorni di soggiorno | B7: 90
A8: Quota tranche 1 (arrivo) | B8: 0.8
A9: Quota tranche 2 (partenza) | B9: 0.2 | C9: Subordinata al controllo documentale.
A10: Quota margine Socio 1 | B10: 0.5
A11: Quota margine Socio 2 | B11: 0.5
A13: Ricavi attesi (calcolati)
A14: Ricavo lordo atteso | B14: =B5*B6
A15: Tranche 80% attesa | B15: =B14*B8
A16: Tranche 20% attesa | B16: =B14*B9
A17: Verifica quote | B17: =B8+B9 | C17: Deve valere 100%. Se no, le quote delle tranche non tornano.
A19: Costi variabili stimati — per ospite
A20: Alloggio (90 gg) | C20: DA STIMARE — voce di costo dominante.
A21: Transfert | C21: DA STIMARE — arrivo + partenza.
A22: Mobility | C22: DA STIMARE — spostamenti locali.
A23: Totale per ospite | B23: =SUM(B20:B22)
A25: Proiezione a 36 ospiti
A26: Costi variabili totali | B26: =B23*B5
A27: Margine atteso | B27: =B14-B26
A28: Margine per ospite | B28: =B6-B23
A29: Incidenza costi su ricavi | B29: =IF(B14=0,"",B26/B14)
A30: Quota attesa Socio 1 | B30: =B27*B10
A31: Quota attesa Socio 2 | B31: =B27*B11

Sheet Movimenti
A1: Data | B1: Tipo movimento | C1: Categoria | D1: Descrizione | E1: Ospite / Tranche di riferimento | F1: Importo (€) | G1: Saldo progressivo (€)
G2: =IF($A2="","",0+IF($B2="Incasso",$F2,-$F2))
G3: =IF($A3="","",N(G2)+IF($B3="Incasso",$F3,-$F3))
G4: =IF($A4="","",N(G3)+IF($B4="Incasso",$F4,-$F4))
G5: =IF($A5="","",N(G4)+IF($B5="Incasso",$F5,-$F5))
G6: =IF($A6="","",N(G5)+IF($B6="Incasso",$F6,-$F6))
G7: =IF($A7="","",N(G6)+IF($B7="Incasso",$F7,-$F7))
G8: =IF($A8="","",N(G7)+IF($B8="Incasso",$F8,-$F8))
G9: =IF($A9="","",N(G8)+IF($B9="Incasso",$F9,-$F9))
G10: =IF($A10="","",N(G9)+IF($B10="Incasso",$F10,-$F10))
G11: =IF($A11="","",N(G10)+IF($B11="Incasso",$F11,-$F11))
G12: =IF($A12="","",N(G11)+IF($B12="Incasso",$F12,-$F12))
G13: =IF($A13="","",N(G12)+IF($B13="Incasso",$F13,-$F13))
G14: =IF($A14="","",N(G13)+IF($B14="Incasso",$F14,-$F14))
... G501: =IF($A501="","",N(G500)+IF($B501="Incasso",$F501,-$F501))

Sheet Riepilogo
A1: Riepilogo economico — progetto GEM
A2: Foglio interamente calcolato. Si aggiorna da solo inserendo le righe in 'Movimenti'.
A4: Ricavi
A5: Voce | B5: Effettivo | C5: Atteso | D5: Scostamento
A6: Incassi tranche 80% | B6: =SUMIFS(Movimenti!$F$2:$F$501,Movimenti!$B$2:$B$501,"Incasso",Movimenti!$C$2:$C$501,"Tranche 80%") | C6: =Parametri!B15 | D6: =B6-C6
A7: Incassi tranche 20% | B7: =SUMIFS(Movimenti!$F$2:$F$501,Movimenti!$B$2:$B$501,"Incasso",Movimenti!$C$2:$C$501,"Tranche 20%") | C7: =Parametri!B16 | D7: =B7-C7
A8: Altri incassi | B8: =SUMIFS(Movimenti!$F$2:$F$501,Movimenti!$B$2:$B$501,"Incasso",Movimenti!$C$2:$C$501,"Altro incasso") | C8: 0 | D8: =B8-C8
A9: Totale ricavi incassati | B9: =SUMIFS(Movimenti!$F$2:$F$501,Movimenti!$B$2:$B$501,"Incasso") | C9: =Parametri!B14 | D9: =B9-C9
A11: Costi variabili
A12: Voce | B12: Effettivo | C12: Atteso | D12: Scostamento
A13: Alloggio | B13: =SUMIFS(Movimenti!$F$2:$F$501,Movimenti!$B$2:$B$501,"Costo",Movimenti!$C$2:$C$501,"Alloggio") | C13: =Parametri!B20*Parametri!B5 | D13: =B13-C13
A14: Transfert | B14: =SUMIFS(Movimenti!$F$2:$F$501,Movimenti!$B$2:$B$501,"Costo",Movimenti!$C$2:$C$501,"Transfert") | C14: =Parametri!B21*Parametri!B5 | D14: =B14-C14
A15: Mobility | B15: =SUMIFS(Movimenti!$F$2:$F$501,Movimenti!$B$2:$B$501,"Costo",Movimenti!$C$2:$C$501,"Mobility") | C15: =Parametri!B22*Parametri!B5 | D15: =B15-C15
A16: Altri costi | B16: =SUMIFS(Movimenti!$F$2:$F$501,Movimenti!$B$2:$B$501,"Costo",Movimenti!$C$2:$C$501,"Altro costo") | C16: 0 | D16: =B16-C16
A17: Totale costi sostenuti | B17: =SUMIFS(Movimenti!$F$2:$F$501,Movimenti!$B$2:$B$501,"Costo") | C17: =Parametri!B26 | D17: =B17-C17
A19: Margine e ripartizione 50/50
A20: Voce | B20: Effettivo | C20: Atteso | D20: Scostamento
A21: Margine residuo | B21: =B9-B17 | C21: =Parametri!B27 | D21: =B21-C21
A22: Quota Socio 1 (50%) | B22: =B21*Parametri!B10 | C22: =Parametri!B30 | D22: =B22-C22
A23: Quota Socio 2 (50%) | B23: =B21*Parametri!B11 | C23: =Parametri!B31 | D23: =B23-C23
A24: Marginalità sui ricavi | B24: =IF(B9=0,"",B21/B9) | C24: =IF(Parametri!B14=0,"",Parametri!B27/Parametri!B14) | D24: =B24-C24
A26: Cassa
A27: Voce | B27: Effettivo | C27: Atteso | D27: Scostamento
A28: Distribuzioni gia' prelevate | B28: =SUMIFS(Movimenti!$F$2:$F$501,Movimenti!$B$2:$B$501,"Distribuzione")
A29: Margine ancora da distribuire | B29: =B21-B28
A30: Saldo di cassa | B30: =B9-B17-B28
A31: Verifica vs ultimo saldo progressivo | B31: =SUMIFS(Movimenti!$F$2:$F$501,Movimenti!$B$2:$B$501,"Incasso")-SUMIFS(Movimenti!$F$2:$F$501,Movimenti!$B$2:$B$501,"Costo")-SUMIFS(Movimenti!$F$2:$F$501,Movimenti!$B$2:$B$501,"Distribuzione")
A33: Avanzamento
A34: Voce | B34: Effettivo | C34: Atteso | D34: Scostamento
A35: Ricavi incassati sul totale atteso | B35: =IF(Parametri!B14=0,"",B9/Parametri!B14)
A36: Numero movimenti registrati | B36: =COUNTA(Movimenti!$A$2:$A$501)
A38: Nota: 'Atteso' deriva dai Parametri (36 ospiti x 2.000 €). 'Effettivo' somma solo i movimenti realmente registrati.
